njbpy/__init__.py
njbpy/_njbpy.py
njbpy-0.0.1.dist-info/METADATA
njbpy-0.0.1.dist-info/WHEEL
njbpy-0.0.1.dist-info/licenses/LICENSE
njbpy-0.0.1.dist-info/RECORD
