Metadata-Version: 2.3
Name: njbpy
Version: 0.0.1
Summary: Utilities created for and used by Noah Blair
Project-URL: Homepage, https://github.com/sodium-hydroxide/blutils
Project-URL: Repository, https://github.com/sodium-hydroxide/blutils.git
Author-email: Noah Blair <noahjblair@outlook.com>
Maintainer-email: Noah Blair <noahjblair@outlook.com>
License:                     GNU GENERAL PUBLIC LICENSE
License-File: LICENSE
Keywords: regex,utilities
Requires-Python: >=3.10
Requires-Dist: numpy
